logdna/VERSION
logdna/__init__.py
logdna/configs.py
logdna/logdna.py
logdna/utils.py
logdna-1.18.12.dist-info/LICENSE
logdna-1.18.12.dist-info/METADATA
logdna-1.18.12.dist-info/WHEEL
logdna-1.18.12.dist-info/top_level.txt
logdna-1.18.12.dist-info/RECORD
