Metadata-Version: 2.1
Name: logdna
Version: 1.18.12
Summary: A Python Package for Sending Logs to LogDNA
Home-page: https://github.com/logdna/python
Download-URL: https://github.com/logdna/python/tarball/1.18.12
Author: LogDNA Inc.
Author-email: help@logdna.com
License: MIT
Keywords: logdna,logging,logs,python,logdna.com,logger
Classifier: Topic :: System :: Logging
Classifier: Programming Language :: Python :: 3
Classifier: Programming Language :: Python :: 3.6
Classifier: Programming Language :: Python :: 3.7
Classifier: Programming Language :: Python :: 3.8
Classifier: Programming Language :: Python :: 3.9
License-File: LICENSE
Requires-Dist: requests
